LICENSE
README.md
pyproject.toml
src/random_land_points/__init__.py
src/random_land_points/contains.py
src/random_land_points/continents.py
src/random_land_points/countries.py
src/random_land_points/sampling.py
src/random_land_points/utils.py
src/random_land_points.egg-info/PKG-INFO
src/random_land_points.egg-info/SOURCES.txt
src/random_land_points.egg-info/dependency_links.txt
src/random_land_points.egg-info/requires.txt
src/random_land_points.egg-info/top_level.txt
src/random_land_points/data/10m/ne_10m_admin_0_countries_lakes.VERSION.txt
src/random_land_points/data/10m/ne_10m_admin_0_countries_lakes.cpg
src/random_land_points/data/10m/ne_10m_admin_0_countries_lakes.dbf
src/random_land_points/data/10m/ne_10m_admin_0_countries_lakes.prj
src/random_land_points/data/10m/ne_10m_admin_0_countries_lakes.shp
src/random_land_points/data/10m/ne_10m_admin_0_countries_lakes.shx
src/random_land_points/data/110m/ne_110m_admin_0_countries_lakes.VERSION.txt
src/random_land_points/data/110m/ne_110m_admin_0_countries_lakes.cpg
src/random_land_points/data/110m/ne_110m_admin_0_countries_lakes.dbf
src/random_land_points/data/110m/ne_110m_admin_0_countries_lakes.prj
src/random_land_points/data/110m/ne_110m_admin_0_countries_lakes.shp
src/random_land_points/data/110m/ne_110m_admin_0_countries_lakes.shx
src/random_land_points/data/50m/ne_50m_admin_0_countries_lakes.VERSION.txt
src/random_land_points/data/50m/ne_50m_admin_0_countries_lakes.cpg
src/random_land_points/data/50m/ne_50m_admin_0_countries_lakes.dbf
src/random_land_points/data/50m/ne_50m_admin_0_countries_lakes.prj
src/random_land_points/data/50m/ne_50m_admin_0_countries_lakes.shp
src/random_land_points/data/50m/ne_50m_admin_0_countries_lakes.shx
tests/test_contains.py
tests/test_continents.py
tests/test_core.py
tests/test_countries.py
tests/test_sampling.py