Metadata-Version: 2.1
Name: random-land-points
Version: 1.1.0
Summary: Sampling random points from non-convex polygons and land areas
Author-email: Duncan Eddy <duncan.eddy@gmail.com>
Project-URL: Homepage, https://github.com/duncaneddy/random-land-points
Requires-Python: >=3.11
License-File: LICENSE
Requires-Dist: numpy<3.0.0,>=2.0.0
Requires-Dist: geopandas<2.0.0,>=1.0.0
Requires-Dist: shapely<3.0.0,>=2.0.0
Provides-Extra: dev
Requires-Dist: pytest; extra == "dev"
Requires-Dist: pytest-cov; extra == "dev"
Provides-Extra: examples
Requires-Dist: matplotlib; extra == "examples"
Requires-Dist: cartopy; extra == "examples"
